<?xml version="1.0" encoding="utf-8"?>
<Deck xmlns:xsi="http://www.w3.org/2001/XMLSchema-instance" xmlns:xsd="http://www.w3.org/2001/XMLSchema">
  <Cards>
    <Card>
      <Id>EX1_316</Id>
      <Count>2</Count>
    </Card>
    <Card>
      <Id>CS2_188</Id>
      <Count>2</Count>
    </Card>
    <Card>
      <Id>EX1_319</Id>
      <Count>1</Count>
    </Card>
    <Card>
      <Id>CS2_065</Id>
      <Count>1</Count>
    </Card>
    <Card>
      <Id>LOE_023</Id>
      <Count>2</Count>
    </Card>
    <Card>
      <Id>EX1_162</Id>
      <Count>2</Count>
    </Card>
    <Card>
      <Id>FP1_002</Id>
      <Count>2</Count>
    </Card>
    <Card>
      <Id>CS2_203</Id>
      <Count>1</Count>
    </Card>
    <Card>
      <Id>NEW1_019</Id>
      <Count>2</Count>
    </Card>
    <Card>
      <Id>FP1_007</Id>
      <Count>2</Count>
    </Card>
    <Card>
      <Id>EX1_005</Id>
      <Count>1</Count>
    </Card>
    <Card>
      <Id>BRM_006</Id>
      <Count>2</Count>
    </Card>
    <Card>
      <Id>GVG_045</Id>
      <Count>2</Count>
    </Card>
    <Card>
      <Id>EX1_093</Id>
      <Count>2</Count>
    </Card>
    <Card>
      <Id>GVG_107</Id>
      <Count>1</Count>
    </Card>
    <Card>
      <Id>EX1_116</Id>
      <Count>1</Count>
    </Card>
    <Card>
      <Id>FP1_030</Id>
      <Count>1</Count>
    </Card>
    <Card>
      <Id>GVG_110</Id>
      <Count>1</Count>
    </Card>
    <Card>
      <Id>EX1_586</Id>
      <Count>2</Count>
    </Card>
  </Cards>
  <Class>Warlock</Class>
  <HearthStatsDeckVersionId>8397450</HearthStatsDeckVersionId>
  <HearthStatsId>7476303</HearthStatsId>
  <LastEdited>2016-02-21T23:53:51.9526065-06:00</LastEdited>
  <MissingCards />
  <Url>http://www.hearthstonetopdecks.com/decks/chakkis-na-winter-prelims-2016-warlock-zoo/</Url>
  <Version>
    <Build>0</Build>
    <Major>1</Major>
    <Minor>0</Minor>
    <Revision>0</Revision>
  </Version>
  <DeckHistory />
  <Archived>false</Archived>
  <Note />
  <SelectedVersion>
    <Build>0</Build>
    <Major>1</Major>
    <Minor>0</Minor>
    <Revision>0</Revision>
  </SelectedVersion>
  <HearthStatsIdsAlreadyReset>false</HearthStatsIdsAlreadyReset>
  <IsArenaDeck>false</IsArenaDeck>
  <DeckId>7017b819-5ed2-4874-91f2-5af4f715af0d</DeckId>
  <Name>ZOO</Name>
  <SyncWithHearthStats>true</SyncWithHearthStats>
  <Tags />
  <HearthStatsIdForUploading>7476303</HearthStatsIdForUploading>
</Deck>